eisen_deploy/__init__.py
eisen_deploy/client/__init__.py
eisen_deploy/client/client.py
eisen_deploy/packaging/__init__.py
eisen_deploy/packaging/packmodel.py
eisen_deploy/serving/__init__.py
eisen_deploy/serving/handlers.py
eisen_deploy-0.0.2.dist-info/LICENSE
eisen_deploy-0.0.2.dist-info/METADATA
eisen_deploy-0.0.2.dist-info/WHEEL
eisen_deploy-0.0.2.dist-info/entry_points.txt
eisen_deploy-0.0.2.dist-info/top_level.txt
eisen_deploy-0.0.2.dist-info/RECORD
