Metadata-Version: 2.1
Name: eisen-deploy
Version: 0.0.2
Summary: Eisen deploy provides model deployment and serving functionality
Home-page: UNKNOWN
License: UNKNOWN
Platform: UNKNOWN
Requires-Python: >=3.6
Requires-Dist: numpy (>=1.18.0)
Requires-Dist: torch (==1.5.0)
Requires-Dist: torchvision (==0.6.0)
Requires-Dist: torch-model-archiver (==0.1.0b20200409)
Requires-Dist: torchserve (==0.0.1b20200409)
